HISTORY.rst
LICENSE
MANIFEST.in
README.rst
architecture.png
setup.py
doc/Makefile
doc/conf.py
doc/index.rst
doc/lightstreamer_adapter.interfaces.rst
doc/lightstreamer_adapter.rst
doc/make.bat
doc/requirements.txt
doc/_static/classic.css
lightstreamer_adapter/__init__.py
lightstreamer_adapter/data_protocol.py
lightstreamer_adapter/metadata_protocol.py
lightstreamer_adapter/protocol.py
lightstreamer_adapter/server.py
lightstreamer_adapter/subscription.py
lightstreamer_adapter.egg-info/PKG-INFO
lightstreamer_adapter.egg-info/SOURCES.txt
lightstreamer_adapter.egg-info/dependency_links.txt
lightstreamer_adapter.egg-info/top_level.txt
lightstreamer_adapter/interfaces/__init__.py
lightstreamer_adapter/interfaces/data.py
lightstreamer_adapter/interfaces/metadata.py
tests/__init__.py
tests/common.py
tests/test_data.py
tests/test_data_protocol.py
tests/test_metadata.py
tests/test_metadata_protocol.py