Metadata-Version: 2.1
Name: lightstreamer-adapter
Version: 1.3.0
Summary: Lightstreamer SDK for Python Adapters
Home-page: https://github.com/Lightstreamer/Lightstreamer-lib-python-adapter
Author: Lightstreamer Srl
Author-email: support@lightstreamer.com
License: Apache License 2.0
Keywords: lightstreamer push realtime real-time
Classifier: Development Status :: 5 - Production/Stable
Classifier: Intended Audience :: Developers
Classifier: License :: OSI Approved :: Apache Software License
Classifier: Natural Language :: English
Classifier: Operating System :: OS Independent
Classifier: Programming Language :: Python :: 3.4
Classifier: Programming Language :: Python :: 3.5
Classifier: Topic :: Communications
Classifier: Topic :: Software Development :: Libraries
Classifier: Topic :: Software Development :: Libraries :: Application Frameworks
License-File: LICENSE
